LICENSE.txt
setup.py
PeakDetective/__init__.py
PeakDetective/detection_helper.py
PeakDetective/find_peaks.R
PeakDetective/install_R_packages.R
PeakDetective/mz_unity.R
PeakDetective.egg-info/PKG-INFO
PeakDetective.egg-info/SOURCES.txt
PeakDetective.egg-info/dependency_links.txt
PeakDetective.egg-info/requires.txt
PeakDetective.egg-info/top_level.txt