Metadata-Version: 2.1
Name: PeakDetective
Version: 0.2.0
Summary: Curates and detects LC/MS peaks in metabolomics datasets
Home-page: https://github.com/e-stan/PeakDetective/
Download-URL: https://github.com/e-stan/PeakDetective/archive/v0.2.0.tar.gz
Author: Ethan Stancliffe
Author-email: estancl1234@gmail.com
License: MIT
Keywords: Metabolomics,LC/MS,Deep Learning,semi-supervised learning,machine learning
Classifier: Development Status :: 3 - Alpha
Classifier: Intended Audience :: Developers
Classifier: Topic :: Software Development :: Build Tools
Classifier: License :: OSI Approved :: MIT License
Classifier: Programming Language :: Python :: 3.7
License-File: LICENSE.txt
